di/__init__.py
di/analysis.py
di/insights.py
swagger_client/__init__.py
swagger_client/api_client.py
swagger_client/configuration.py
swagger_client/rest.py
swagger_client/api/__init__.py
swagger_client/api/analysis_api.py
swagger_client/api/boards_api.py
swagger_client/api/datasets_api.py
swagger_client/api/insights_api.py
swagger_client/api/projects_api.py
swagger_client/api/teams_api.py
swagger_client/api/users_api.py
swagger_client/models/__init__.py
swagger_client/models/algorithm.py
swagger_client/models/analysis_job.py
swagger_client/models/analysis_job_description.py
swagger_client/models/analysis_job_description_datasource.py
swagger_client/models/analysis_job_status.py
swagger_client/models/board.py
swagger_client/models/data_file.py
swagger_client/models/dataset.py
swagger_client/models/error_message.py
swagger_client/models/insight.py
swagger_client/models/patch_action.py
swagger_client/models/project.py
swagger_client/models/project_sub.py
swagger_client/models/team.py
swagger_client/models/token.py
swagger_client/models/topic.py
swagger_client/models/user.py
42di-0.2.6.dist-info/METADATA
42di-0.2.6.dist-info/WHEEL
42di-0.2.6.dist-info/top_level.txt
42di-0.2.6.dist-info/RECORD
