Metadata-Version: 2.1
Name: 42di
Version: 0.2.6
Summary: 42di is the python sdk for 42di.com
Home-page: https://42di.com
Author-email: support@42di.com
License: UNKNOWN
Keywords: 42DI,42di Python SDK,42di.com,42di.cn
Platform: UNKNOWN
Requires-Dist: urllib3 (>=1.15)
Requires-Dist: six (>=1.10)
Requires-Dist: certifi
Requires-Dist: python-dateutil
